codercore/__init__.py
codercore/types.py
codercore/db/__init__.py
codercore/db/aggregation.py
codercore/db/models.py
codercore/db/pagination.py
codercore/lib/__init__.py
codercore/lib/aggregation.py
codercore/lib/collection.py
codercore/lib/hash.py
codercore/lib/redis.py
codercore/lib/settings.py
codercore/lib/version.py
codercore/lib/http/__init__.py
codercore/lib/http/exceptions.py
codercore/lib/schemas/__init__.py
codercore/lib/schemas/pydantic.py
codercore/test/__init__.py
codercore/test/fixtures.py
codercore/test/pydantic.py
codercore-8.1.3.dist-info/METADATA
codercore-8.1.3.dist-info/WHEEL
codercore-8.1.3.dist-info/top_level.txt
codercore-8.1.3.dist-info/RECORD
