Metadata-Version: 2.4
Name: codercore
Version: 8.1.3
Summary: codercore
Author-email: Code R <hello@coderstudio.dev>
Requires-Dist: aiohttp~=3.8
Requires-Dist: asyncpg~=0.27
Requires-Dist: asyncstdlib~=3.10
Requires-Dist: bcrypt~=4.0
Requires-Dist: cloud-sql-python-connector[asyncpg]~=1.1
Requires-Dist: frozendict~=2.4
Requires-Dist: psycopg2~=2.9
Requires-Dist: pydantic~=2.4
Requires-Dist: pytest~=7.2
Requires-Dist: redis~=5.0
Requires-Dist: sqlalchemy[asyncio]~=2.0
Requires-Dist: sqlalchemy-utils~=0.41
Provides-Extra: test
Requires-Dist: pytest-asyncio~=0.20; extra == "test"
Requires-Dist: pytest-cov~=4.0; extra == "test"
Requires-Dist: pytest-mock~=3.10; extra == "test"
Requires-Dist: pytest-xdist[psutil]~=3.0; extra == "test"
Provides-Extra: dev
Requires-Dist: black~=22.10; extra == "dev"
Requires-Dist: flake8~=6.0; extra == "dev"
Requires-Dist: isort~=5.11; extra == "dev"
